setup.py
simple_pickle/utils.py
simple_pickle.egg-info/PKG-INFO
simple_pickle.egg-info/SOURCES.txt
simple_pickle.egg-info/dependency_links.txt
simple_pickle.egg-info/top_level.txt