Metadata-Version: 1.0
Name: simple-pickle
Version: 1.0.0
Summary: easy utils for pickle load/dump and write/read file
Home-page: UNKNOWN
Author: Haydon
Author-email: 13261051171@163.com
License: UNKNOWN
Platform: UNKNOWN
